QNotifications/QNotification.py
QNotifications/QNotificationArea.py
QNotifications/__init__.py
QNotifications/abstractions.py
python_qnotifications-2.0.6.dist-info/METADATA
python_qnotifications-2.0.6.dist-info/WHEEL
python_qnotifications-2.0.6.dist-info/top_level.txt
python_qnotifications-2.0.6.dist-info/RECORD
