Metadata-Version: 2.1
Name: python-qnotifications
Version: 2.0.6
Summary: Pretty in-app notifications for PyQt
Home-page: https://github.com/dschreij/QNotifications
Author: Daniel Schreij
Author-email: dschreij@gmail.com
License: UNKNOWN
Platform: UNKNOWN
Classifier: Intended Audience :: Developers
Classifier: Topic :: Desktop Environment
Classifier: Operating System :: MacOS :: MacOS X
Classifier: Operating System :: Microsoft :: Windows
Classifier: Operating System :: POSIX
Classifier: License :: OSI Approved :: GNU Lesser General Public License v3 (LGPLv3)
Classifier: Programming Language :: Python :: 2
Classifier: Programming Language :: Python :: 3
Requires-Dist: qtpy
